frostbyte/__init__.py
frostbyte-0.dist-info/LICENSE
frostbyte-0.dist-info/METADATA
frostbyte-0.dist-info/WHEEL
frostbyte-0.dist-info/top_level.txt
frostbyte-0.dist-info/RECORD
