Metadata-Version: 2.1
Name: frostbyte
Version: 0
Summary: Hello, FrostByte!
Home-page: https://github.com/DemieOh/FrostByte
Author: Demian Oh
Author-email: demie.oh@gmail.com
License: UNKNOWN
Platform: UNKNOWN
Requires-Python: >=3.7
